factorial_nhk/__init__.py
factorial_nhk/app.py
factorial_nhk/factorial.py
factorial_nhk-0.1.0.dist-info/METADATA
factorial_nhk-0.1.0.dist-info/WHEEL
factorial_nhk-0.1.0.dist-info/RECORD
