Metadata-Version: 2.1
Name: factorial-nhk
Version: 0.1.0
Summary: 
Author: nguyenhoangkhang
Author-email: nguyenhoangkhang040904@gmail.com
Requires-Python: >=3.11,<4.0
Classifier: Programming Language :: Python :: 3
Classifier: Programming Language :: Python :: 3.11
Classifier: Programming Language :: Python :: 3.12
Requires-Dist: streamlit (>=1.33.0,<2.0.0)
